iot_gw/__init__.py
iot_gw/device.py
iot_gw/gateway.py
iot_gw/bridge/__init__.py
iot_gw/bridge/adapter.py
iot_gw/bridge/factory.py
iot_gw/bridge/gcp.py
iot_gw/proxy/__init__.py
iot_gw/proxy/adapter.py
iot_gw/proxy/mqtt.py
tests/__init__.py
tests/bridge_factory_test.py
tests/device_manager_test.py
tests/device_test.py
tests/gateway_test.py
tests/gcp_bridge_test.py
tests/mqtt_proxy_test.py
iot_gw-0.1.dev53.dist-info/LICENSE
iot_gw-0.1.dev53.dist-info/METADATA
iot_gw-0.1.dev53.dist-info/WHEEL
iot_gw-0.1.dev53.dist-info/top_level.txt
iot_gw-0.1.dev53.dist-info/RECORD
