Metadata-Version: 2.1
Name: iot-gw
Version: 0.1.dev53
Summary: IoT gateway
Home-page: https://github.com/arnlec/iot-gw
Author: A. LE CANN
Author-email: arnaud@lecann.com
License: GPLv3
Platform: UNKNOWN
Classifier: Programming Language :: Python :: 3
Classifier: Operating System :: OS Independent
Classifier: License :: OSI Approved :: GNU General Public License v3 (GPLv3)
Requires-Python: >=3
Requires-Dist: pyjwt (==1.7.1)
Requires-Dist: cryptography (==2.7)
Requires-Dist: flask (==1.1.1)
Requires-Dist: paho-mqtt (==1.4.0)
Requires-Dist: PyYAML (==5.2)
